odoo/addons/shopinvader_search_engine_product_stock_state/README.rst
odoo/addons/shopinvader_search_engine_product_stock_state/__init__.py
odoo/addons/shopinvader_search_engine_product_stock_state/__manifest__.py
odoo/addons/shopinvader_search_engine_product_stock_state/i18n/shopinvader_product_stock_state.pot
odoo/addons/shopinvader_search_engine_product_stock_state/i18n/shopinvader_search_engine_product_stock_state.pot
odoo/addons/shopinvader_search_engine_product_stock_state/models/__init__.py
odoo/addons/shopinvader_search_engine_product_stock_state/models/product_product.py
odoo/addons/shopinvader_search_engine_product_stock_state/models/se_backend.py
odoo/addons/shopinvader_search_engine_product_stock_state/readme/CONFIGURE.rst
odoo/addons/shopinvader_search_engine_product_stock_state/readme/CONTRIBUTORS.rst
odoo/addons/shopinvader_search_engine_product_stock_state/readme/CREDITS.rst
odoo/addons/shopinvader_search_engine_product_stock_state/readme/DESCRIPTION.rst
odoo/addons/shopinvader_search_engine_product_stock_state/readme/USAGE.rst
odoo/addons/shopinvader_search_engine_product_stock_state/static/description/index.html
odoo/addons/shopinvader_search_engine_product_stock_state/tests/__init__.py
odoo/addons/shopinvader_search_engine_product_stock_state/tests/test_product.py
odoo_addon_shopinvader_search_engine_product_stock_state-16.0.1.0.0.4.dist-info/METADATA
odoo_addon_shopinvader_search_engine_product_stock_state-16.0.1.0.0.4.dist-info/WHEEL
odoo_addon_shopinvader_search_engine_product_stock_state-16.0.1.0.0.4.dist-info/top_level.txt
odoo_addon_shopinvader_search_engine_product_stock_state-16.0.1.0.0.4.dist-info/RECORD
